Metadata-Version: 2.4
Name: tgext.pluggable
Version: 0.8.5
Summary: Plug applications and extensions in a TurboGears2 project
Home-page: https://github.com/TurboGears/tgext.pluggable
Author: Alessandro Molina, Jaroslav Mikulík
Author-email: alessandro.molina@axant.it, byczech@gmail.com
License: MIT
Keywords: turbogears2.extension
Classifier: Environment :: Web Environment
Classifier: Topic :: Software Development :: Libraries :: Python Modules
Classifier: Framework :: TurboGears
Requires-Dist: TurboGears2>=2.3.0
Requires-Dist: gearbox
Dynamic: author
Dynamic: author-email
Dynamic: classifier
Dynamic: description
Dynamic: home-page
Dynamic: keywords
Dynamic: license
Dynamic: requires-dist
Dynamic: summary
